{
  "kind": "collectionType",
  "collectionName": "promotions",
  "info": {
    "singularName": "promotion",
    "pluralName": "promotions",
    "displayName": "Promotion",
    "description": ""
  },
  "options": {
    "draftAndPublish": false
  },
  "pluginOptions": {},
  "attributes": {
    "banner_img": {
      "type": "media",
      "multiple": false,
      "required": false,
      "allowedTypes": [
        "images",
        "files",
        "videos",
        "audios"
      ]
    },
    "position": {
      "type": "enumeration",
      "enum": [
        "top",
        "bottom"
      ]
    },
    "isActive": {
      "type": "boolean"
    },
    "popup_img": {
      "allowedTypes": [
        "images",
        "files",
        "videos",
        "audios"
      ],
      "type": "media",
      "multiple": false
    }
  }
}
